pg_diagram/__init__.py
pg_diagram/__main__.py
pg_diagram/graph.py
pg_diagram/parsing.py
pg_diagram-0.2.0.dist-info/WHEEL
pg_diagram-0.2.0.dist-info/entry_points.txt
pg_diagram-0.2.0.dist-info/METADATA
pg_diagram-0.2.0.dist-info/RECORD
