Metadata-Version: 2.3
Name: pg-diagram
Version: 0.2.0
Summary: A tool for creating ER diagrams from postgresql database schemas
Requires-Dist: graphviz>=0.20.3
Requires-Dist: sqlglot>=26.24.0
Requires-Python: >=3.12
